bitbound/__init__.py
bitbound/device.py
bitbound/event.py
bitbound/expression.py
bitbound/hardware.py
bitbound/units.py
bitbound/buses/__init__.py
bitbound/buses/base.py
bitbound/buses/gpio.py
bitbound/buses/i2c.py
bitbound/buses/onewire.py
bitbound/buses/spi.py
bitbound/buses/uart.py
bitbound/devices/__init__.py
bitbound/devices/actuators/__init__.py
bitbound/devices/actuators/buzzer.py
bitbound/devices/actuators/led.py
bitbound/devices/actuators/motor.py
bitbound/devices/actuators/relay.py
bitbound/devices/displays/__init__.py
bitbound/devices/displays/lcd.py
bitbound/devices/displays/oled.py
bitbound/devices/displays/segment.py
bitbound/devices/sensors/__init__.py
bitbound/devices/sensors/analog.py
bitbound/devices/sensors/bme280.py
bitbound/devices/sensors/dht.py
bitbound/devices/sensors/ds18b20.py
bitbound/devices/sensors/light.py
bitbound/devices/sensors/motion.py
bitbound-0.1.0.dist-info/licenses/LICENSE
bitbound-0.1.0.dist-info/METADATA
bitbound-0.1.0.dist-info/WHEEL
bitbound-0.1.0.dist-info/top_level.txt
bitbound-0.1.0.dist-info/RECORD
