Metadata-Version: 2.4
Name: bitbound
Version: 0.1.0
Summary: High-Level Embedded Python Library for declarative hardware programming
Home-page: https://github.com/bitbound/bitbound
Author: BitBound Team
Author-email: BitBound Team <contact@bitbound.io>
License: MIT
Project-URL: Homepage, https://github.com/bitbound/bitbound
Project-URL: Documentation, https://bitbound.readthedocs.io/
Project-URL: Repository, https://github.com/bitbound/bitbound
Project-URL: Issues, https://github.com/bitbound/bitbound/issues
Keywords: embedded,micropython,hardware,iot,sensors,gpio,i2c,spi,raspberry-pi,esp32,arduino
Classifier: Development Status :: 3 - Alpha
Classifier: Intended Audience :: Developers
Classifier: Intended Audience :: Education
Classifier: Intended Audience :: Science/Research
Classifier: License :: OSI Approved :: MIT License
Classifier: Operating System :: OS Independent
Classifier: Programming Language :: Python :: 3
Classifier: Programming Language :: Python :: 3.7
Classifier: Programming Language :: Python :: 3.8
Classifier: Programming Language :: Python :: 3.9
Classifier: Programming Language :: Python :: 3.10
Classifier: Programming Language :: Python :: 3.11
Classifier: Programming Language :: Python :: 3.12
Classifier: Programming Language :: Python :: 3.13
Classifier: Programming Language :: Python :: Implementation :: MicroPython
Classifier: Topic :: System :: Hardware
Classifier: Topic :: Software Development :: Embedded Systems
Classifier: Topic :: Scientific/Engineering
Requires-Python: >=3.7
License-File: LICENSE
Provides-Extra: dev
Requires-Dist: pytest>=6.0; extra == "dev"
Requires-Dist: pytest-cov>=2.0; extra == "dev"
Requires-Dist: black>=22.0; extra == "dev"
Requires-Dist: mypy>=0.9; extra == "dev"
Requires-Dist: build; extra == "dev"
Requires-Dist: twine; extra == "dev"
Dynamic: author
Dynamic: home-page
Dynamic: license-file
Dynamic: requires-python
